<?xml version="1.0" encoding="UTF-8"?>
<ElevationResponse>
 <status>OK</status>
 <result>
  <location>
   <lat>35.6220940</lat>
   <lng>139.7477703</lng>
  </location>
  <elevation>2.7739751</elevation>
  <resolution>0.5964970</resolution>
 </result>
 <result>
  <location>
   <lat>52.9009133</lat>
   <lng>-168.1990776</lng>
  </location>
  <elevation>-407.5320129</elevation>
  <resolution>610.8129272</resolution>
 </result>
 <result>
  <location>
   <lat>49.1924387</lat>
   <lng>-136.9446671</lng>
  </location>
  <elevation>-3883.1040039</elevation>
  <resolution>610.8129272</resolution>
 </result>
 <result>
  <location>
   <lat>44.0493615</lat>
   <lng>163.7541937</lng>
  </location>
  <elevation>-5759.6362305</elevation>
  <resolution>610.8129272</resolution>
 </result>
 <result>
  <location>
   <lat>39.5785948</lat>
   <lng>-177.2380065</lng>
  </location>
  <elevation>-5432.7768555</elevation>
  <resolution>610.8129272</resolution>
 </result>
 <result>
  <location>
   <lat>45.5320828</lat>
   <lng>-123.0053566</lng>
  </location>
  <elevation>43.8696175</elevation>
  <resolution>4.7719760</resolution>
 </result>
</ElevationResponse>
